{"dimmed":{"inactive":"#23223d","subtle":"#565393"},"built_in":{"keyword":"#fb5c8e","function":"#a29dff","constant":"#b4a4de","variable":"#93c5e6","type":"#f7d98d"},"yellow":"#f7d98d","green":"#adcfbc","bg":{"base":"#1a1a2e","selected":"#2c223c","alt":"#2c223c"},"directory":"#df8b92","gitsigns":{"change":"#ea6634","remove":"#e83f80","text":"#b3dfef","add":"#adcfbc"},"scheme-name":"amora","fg":"#dedbeb","accent":"#f09eed","pum":{"fg":"#dedbeb","sbar":"#313a43","thumb":"#b3dfef","bg":"#565393","sel":{"bg":"#a29dff","fg":"#161627"}},"border":"#b4a4de","inc_search":{"fg":"#1a1a2e","bg":"#e83f80"},"blue":"#bdceed","orange":"#ea6634","search_result":{"bg":"#e83f80","fg":"#1a1a2e","telescope":"#ed86ea"},"diff":{"change":"#ea6634","remove":"#e83f80","text":"#b3dfef","add":"#adcfbc"},"heading":{"h1":"#9985d1","h2":"#b4a4de"},"uri":"#84c49b","magenta":"#9985d1","red":"#e83f80","diagnostic":{"hint":"#93c5e6","warn":"#f79f79","info":"#adcfbc","error":"#e83f80"},"syntax":{"tag":"#aed9f6","statement":"#f09eed","field":"#ff9f50","constructor":"#ed86ea","identifier":"#84c49b","struct":"#f6e08b","punctuation":"#e68ac1","string":"#9fd3b3","function":"#a29dff","conditional":"#df8b92","property":"#b2aeff","comment":"#565393","number":"#b4a4de","type":"#93c5e6","include":"#fb5c8e","preproc":"#ffb65e","constant":"#b4a4de","operator":"#e68ac1","todo":{"fg":"#dedbeb","bg":"#e83f80"},"parameter":"#f79f79","keyword":"#ed3f7f","variable":"#dedbeb"},"cyan":"#a2baa8","match":"#6c8391"}