{"diagnostic":{"hint":"#93c5e6","error":"#e83f80","warn":"#f79f79","info":"#adcfbc"},"dimmed":{"subtle":"#565393","inactive":"#23223d"},"inc_search":{"bg":"#e83f80","fg":"#1a1a2e"},"red":"#e83f80","pum":{"bg":"#565393","sel":{"fg":"#161627","bg":"#a29dff"},"fg":"#dedbeb","sbar":"#313a43","thumb":"#b3dfef"},"green":"#adcfbc","uri":"#84c49b","diff":{"text":"#b3dfef","remove":"#e83f80","add":"#adcfbc","change":"#ea6634"},"gitsigns":{"text":"#b3dfef","remove":"#e83f80","add":"#adcfbc","change":"#ea6634"},"magenta":"#9985d1","blue":"#bdceed","scheme-name":"amora","heading":{"h2":"#b4a4de","h1":"#9985d1"},"accent":"#f09eed","fg":"#dedbeb","border":"#b4a4de","orange":"#ea6634","syntax":{"function":"#a29dff","include":"#fb5c8e","statement":"#f09eed","identifier":"#84c49b","conditional":"#df8b92","struct":"#f6e08b","type":"#93c5e6","number":"#b4a4de","constructor":"#ed86ea","constant":"#b4a4de","todo":{"bg":"#e83f80","fg":"#dedbeb"},"operator":"#e68ac1","parameter":"#f79f79","preproc":"#ffb65e","keyword":"#ed3f7f","comment":"#565393","tag":"#aed9f6","property":"#b2aeff","punctuation":"#e68ac1","string":"#9fd3b3","variable":"#dedbeb","field":"#ff9f50"},"directory":"#df8b92","yellow":"#f7d98d","bg":{"alt":"#2c223c","selected":"#2c223c","base":"#1a1a2e"},"match":"#6c8391","cyan":"#a2baa8","search_result":{"fg":"#1a1a2e","telescope":"#ed86ea","bg":"#e83f80"},"built_in":{"keyword":"#fb5c8e","type":"#f7d98d","function":"#a29dff","variable":"#93c5e6","constant":"#b4a4de"}}