{"pum":{"thumb":"#b3dfef","sbar":"#313a43","bg":"#565393","fg":"#dedbeb","sel":{"bg":"#a29dff","fg":"#161627"}},"match":"#6c8391","bg":{"base":"#1a1a2e","selected":"#2c223c","alt":"#2c223c"},"search_result":{"telescope":"#ed86ea","fg":"#1a1a2e","bg":"#e83f80"},"fg":"#dedbeb","built_in":{"function":"#a29dff","type":"#f7d98d","variable":"#93c5e6","keyword":"#fb5c8e","constant":"#b4a4de"},"magenta":"#9985d1","syntax":{"preproc":"#ffb65e","tag":"#aed9f6","identifier":"#84c49b","statement":"#f09eed","parameter":"#f79f79","function":"#a29dff","constant":"#b4a4de","comment":"#565393","variable":"#dedbeb","include":"#fb5c8e","todo":{"fg":"#dedbeb","bg":"#e83f80"},"punctuation":"#e68ac1","type":"#93c5e6","struct":"#f6e08b","constructor":"#ed86ea","number":"#b4a4de","conditional":"#df8b92","string":"#9fd3b3","operator":"#e68ac1","property":"#b2aeff","keyword":"#ed3f7f","field":"#ff9f50"},"yellow":"#f7d98d","diff":{"change":"#ea6634","text":"#b3dfef","add":"#adcfbc","remove":"#e83f80"},"blue":"#bdceed","orange":"#ea6634","dimmed":{"inactive":"#23223d","subtle":"#565393"},"cyan":"#a2baa8","heading":{"h1":"#9985d1","h2":"#b4a4de"},"green":"#adcfbc","border":"#b4a4de","inc_search":{"fg":"#1a1a2e","bg":"#e83f80"},"uri":"#84c49b","red":"#e83f80","directory":"#df8b92","gitsigns":{"change":"#ea6634","text":"#b3dfef","add":"#adcfbc","remove":"#e83f80"},"diagnostic":{"hint":"#93c5e6","warn":"#f79f79","error":"#e83f80","info":"#adcfbc"},"accent":"#f09eed","scheme-name":"amora"}