{"fg":"#dedbeb","gitsigns":{"remove":"#e83f80","text":"#b3dfef","change":"#ea6634","add":"#adcfbc"},"match":"#6c8391","uri":"#84c49b","dimmed":{"subtle":"#565393","inactive":"#23223d"},"inc_search":{"bg":"#e83f80","fg":"#1a1a2e"},"blue":"#bdceed","orange":"#ea6634","accent":"#f09eed","green":"#adcfbc","scheme-name":"amora","built_in":{"constant":"#b4a4de","function":"#a29dff","keyword":"#fb5c8e","variable":"#93c5e6","type":"#f7d98d"},"heading":{"h2":"#b4a4de","h1":"#9985d1"},"pum":{"thumb":"#b3dfef","fg":"#dedbeb","sbar":"#313a43","bg":"#565393","sel":{"fg":"#161627","bg":"#a29dff"}},"cyan":"#a2baa8","diagnostic":{"hint":"#93c5e6","info":"#adcfbc","warn":"#f79f79","error":"#e83f80"},"diff":{"remove":"#e83f80","text":"#b3dfef","change":"#ea6634","add":"#adcfbc"},"red":"#e83f80","syntax":{"field":"#ff9f50","statement":"#f09eed","preproc":"#ffb65e","keyword":"#ed3f7f","function":"#a29dff","type":"#93c5e6","struct":"#f6e08b","conditional":"#df8b92","punctuation":"#e68ac1","variable":"#dedbeb","constant":"#b4a4de","comment":"#565393","number":"#b4a4de","operator":"#e68ac1","string":"#9fd3b3","include":"#fb5c8e","identifier":"#84c49b","tag":"#aed9f6","constructor":"#ed86ea","todo":{"bg":"#e83f80","fg":"#dedbeb"},"property":"#b2aeff","parameter":"#f79f79"},"border":"#b4a4de","directory":"#df8b92","bg":{"selected":"#2c223c","alt":"#2c223c","base":"#1a1a2e"},"search_result":{"fg":"#1a1a2e","telescope":"#ed86ea","bg":"#e83f80"},"yellow":"#f7d98d","magenta":"#9985d1"}