{"accent":"#f09eed","bg":{"base":"#1a1a2e","selected":"#2c223c","alt":"#2c223c"},"match":"#6c8391","uri":"#84c49b","yellow":"#f7d98d","built_in":{"keyword":"#fb5c8e","type":"#f7d98d","function":"#a29dff","constant":"#b4a4de","variable":"#93c5e6"},"orange":"#ea6634","gitsigns":{"remove":"#e83f80","add":"#adcfbc","text":"#b3dfef","change":"#ea6634"},"search_result":{"bg":"#e83f80","fg":"#1a1a2e","telescope":"#ed86ea"},"scheme-name":"amora","heading":{"h2":"#b4a4de","h1":"#9985d1"},"diagnostic":{"hint":"#93c5e6","warn":"#f79f79","info":"#adcfbc","error":"#e83f80"},"pum":{"bg":"#565393","thumb":"#b3dfef","sel":{"bg":"#a29dff","fg":"#161627"},"fg":"#dedbeb","sbar":"#313a43"},"diff":{"remove":"#e83f80","add":"#adcfbc","text":"#b3dfef","change":"#ea6634"},"inc_search":{"fg":"#1a1a2e","bg":"#e83f80"},"red":"#e83f80","syntax":{"preproc":"#ffb65e","constructor":"#ed86ea","variable":"#dedbeb","keyword":"#ed3f7f","conditional":"#df8b92","type":"#93c5e6","statement":"#f09eed","field":"#ff9f50","number":"#b4a4de","todo":{"fg":"#dedbeb","bg":"#e83f80"},"tag":"#aed9f6","string":"#9fd3b3","punctuation":"#e68ac1","parameter":"#f79f79","property":"#b2aeff","include":"#fb5c8e","struct":"#f6e08b","operator":"#e68ac1","comment":"#565393","identifier":"#84c49b","constant":"#b4a4de","function":"#a29dff"},"directory":"#df8b92","border":"#b4a4de","green":"#adcfbc","dimmed":{"subtle":"#565393","inactive":"#23223d"},"fg":"#dedbeb","magenta":"#9985d1","blue":"#bdceed","cyan":"#a2baa8"}