{"bg":{"selected":"#2c223c","base":"#1a1a2e","alt":"#2c223c"},"gitsigns":{"add":"#adcfbc","remove":"#e83f80","text":"#b3dfef","change":"#ea6634"},"yellow":"#f7d98d","scheme-name":"amora","red":"#e83f80","inc_search":{"fg":"#1a1a2e","bg":"#e83f80"},"heading":{"h1":"#9985d1","h2":"#b4a4de"},"directory":"#df8b92","accent":"#f09eed","magenta":"#9985d1","uri":"#84c49b","cyan":"#a2baa8","dimmed":{"subtle":"#565393","inactive":"#23223d"},"pum":{"fg":"#dedbeb","thumb":"#b3dfef","bg":"#565393","sel":{"bg":"#a29dff","fg":"#161627"},"sbar":"#313a43"},"syntax":{"include":"#fb5c8e","type":"#93c5e6","field":"#ff9f50","constructor":"#ed86ea","statement":"#f09eed","keyword":"#ed3f7f","constant":"#b4a4de","tag":"#aed9f6","conditional":"#df8b92","comment":"#565393","function":"#a29dff","todo":{"fg":"#dedbeb","bg":"#e83f80"},"operator":"#e68ac1","preproc":"#ffb65e","identifier":"#84c49b","punctuation":"#e68ac1","number":"#b4a4de","parameter":"#f79f79","string":"#9fd3b3","struct":"#f6e08b","variable":"#dedbeb","property":"#b2aeff"},"diff":{"add":"#adcfbc","remove":"#e83f80","text":"#b3dfef","change":"#ea6634"},"blue":"#bdceed","fg":"#dedbeb","green":"#adcfbc","built_in":{"function":"#a29dff","type":"#f7d98d","keyword":"#fb5c8e","variable":"#93c5e6","constant":"#b4a4de"},"border":"#b4a4de","match":"#6c8391","orange":"#ea6634","diagnostic":{"warn":"#f79f79","error":"#e83f80","hint":"#93c5e6","info":"#adcfbc"},"search_result":{"fg":"#1a1a2e","telescope":"#ed86ea","bg":"#e83f80"}}