{"orange":"#ea6634","diagnostic":{"info":"#adcfbc","warn":"#f79f79","error":"#e83f80","hint":"#93c5e6"},"yellow":"#f7d98d","green":"#adcfbc","bg":{"selected":"#2c223c","base":"#1a1a2e","alt":"#2c223c"},"built_in":{"function":"#a29dff","keyword":"#fb5c8e","type":"#f7d98d","constant":"#b4a4de","variable":"#93c5e6"},"directory":"#df8b92","scheme-name":"amora","fg":"#dedbeb","diff":{"change":"#ea6634","add":"#adcfbc","text":"#b3dfef","remove":"#e83f80"},"blue":"#bdceed","match":"#6c8391","cyan":"#a2baa8","accent":"#f09eed","dimmed":{"subtle":"#565393","inactive":"#23223d"},"heading":{"h2":"#b4a4de","h1":"#9985d1"},"search_result":{"bg":"#e83f80","telescope":"#ed86ea","fg":"#1a1a2e"},"pum":{"sbar":"#313a43","bg":"#565393","thumb":"#b3dfef","sel":{"fg":"#161627","bg":"#a29dff"},"fg":"#dedbeb"},"red":"#e83f80","uri":"#84c49b","inc_search":{"bg":"#e83f80","fg":"#1a1a2e"},"gitsigns":{"change":"#ea6634","add":"#adcfbc","text":"#b3dfef","remove":"#e83f80"},"syntax":{"function":"#a29dff","string":"#9fd3b3","type":"#93c5e6","comment":"#565393","punctuation":"#e68ac1","keyword":"#ed3f7f","struct":"#f6e08b","todo":{"bg":"#e83f80","fg":"#dedbeb"},"constructor":"#ed86ea","statement":"#f09eed","property":"#b2aeff","field":"#ff9f50","variable":"#dedbeb","tag":"#aed9f6","number":"#b4a4de","conditional":"#df8b92","constant":"#b4a4de","preproc":"#ffb65e","operator":"#e68ac1","identifier":"#84c49b","include":"#fb5c8e","parameter":"#f79f79"},"border":"#b4a4de","magenta":"#9985d1"}