{"border":"#b4a4de","search_result":{"telescope":"#ed86ea","bg":"#e83f80","fg":"#1a1a2e"},"green":"#adcfbc","match":"#6c8391","cyan":"#a2baa8","inc_search":{"bg":"#e83f80","fg":"#1a1a2e"},"red":"#e83f80","diagnostic":{"warn":"#f79f79","hint":"#93c5e6","error":"#e83f80","info":"#adcfbc"},"gitsigns":{"text":"#b3dfef","add":"#adcfbc","change":"#ea6634","remove":"#e83f80"},"blue":"#bdceed","scheme-name":"amora","heading":{"h2":"#b4a4de","h1":"#9985d1"},"diff":{"text":"#b3dfef","add":"#adcfbc","change":"#ea6634","remove":"#e83f80"},"orange":"#ea6634","yellow":"#f7d98d","pum":{"sel":{"fg":"#161627","bg":"#a29dff"},"bg":"#565393","sbar":"#313a43","thumb":"#b3dfef","fg":"#dedbeb"},"uri":"#84c49b","built_in":{"variable":"#93c5e6","function":"#a29dff","constant":"#b4a4de","type":"#f7d98d","keyword":"#fb5c8e"},"magenta":"#9985d1","accent":"#f09eed","bg":{"alt":"#2c223c","base":"#1a1a2e","selected":"#2c223c"},"syntax":{"identifier":"#84c49b","tag":"#aed9f6","string":"#9fd3b3","variable":"#dedbeb","comment":"#565393","keyword":"#ed3f7f","conditional":"#df8b92","punctuation":"#e68ac1","operator":"#e68ac1","field":"#ff9f50","struct":"#f6e08b","include":"#fb5c8e","number":"#b4a4de","todo":{"bg":"#e83f80","fg":"#dedbeb"},"constant":"#b4a4de","function":"#a29dff","preproc":"#ffb65e","constructor":"#ed86ea","property":"#b2aeff","parameter":"#f79f79","type":"#93c5e6","statement":"#f09eed"},"dimmed":{"inactive":"#23223d","subtle":"#565393"},"directory":"#df8b92","fg":"#dedbeb"}