{"blue":"#61afef","cyan":"#519ABA","bg":{"alt":"#d0d0d","selected":"#222827","base":"#131316"},"search_result":{"telescope":"#654a96","fg":"#0","bg":"#202727"},"gitsigns":{"change":"#5786bc","text":"#9898ae","add":"#63b0b0","remove":"#cd749c"},"fg":"#e1d9ea","yellow":"#e7c787","scheme-name":"boo","match":"#0","orange":"#e7c787","border":"#222827","uri":"#e4dcec","diff":{"change":"#5786bc","text":"#9898ae","add":"#63b0b0","remove":"#cd749c"},"pum":{"sel":{"bg":"#0","fg":"#0"},"fg":"#9c75dd","thumb":"#9898ae","sbar":"#222827","bg":"#120f12"},"inc_search":{"bg":"#60d0d","fg":"#63b0b0"},"built_in":{"function":"#748a90","type":"#3a7272","variable":"#32547b","keyword":"#654a96","constant":"#4291ad"},"heading":{"h2":"#0","h1":"#0"},"green":"#A3BE8C","syntax":{"constructor":"#63b0b0","property":"#738d8d","struct":"#63b0b0","include":"#63b0b0","field":"#5d6f74","function":"#6eacb8","string":"#72d4d4","operator":"#656568","todo":{"fg":"#3f3442","bg":"#0"},"statement":"#63b0b0","tag":"#85c1c1","number":"#d9d6cf","constant":"#7d6c82","punctuation":"#4b4b4e","type":"#63b0b0","conditional":"#53757e","variable":"#a7d3d3","comment":"#9898ae","preproc":"#63b0b0","keyword":"#5c4489","parameter":"#a9d1df"},"accent":"#654a96","magenta":"#c882e7","dimmed":{"inactive":"#29292e","subtle":"#654a96"},"diagnostic":{"info":"#e4dcec","error":"#c988df","hint":"#5d4663","warn":"#a9d1df"},"cursorlinenr":"#625566"}