{"diagnostic":{"warn":"#fae3b0","error":"#f28fad","info":"#89dceb","hint":"#f5e0dc"},"green":"#ABE9B3","pum":{"fg":"#c3bac6","sel":{"bg":"#575268","fg":"#d9e0ee"},"bg":"#302d41","thumb":"#6e6c7e","sbar":"#575268"},"orange":"#FAE3B0","cursorlinenr":"#abe9b3","fg":"#d9e0ee","uri":"#f5e0dc","accent":"#f5c2e7","yellow":"#FAE3B0","diff":{"add":"#1e1e2e","remove":"#1e1e2e","text":"#1e1e2e","change":"#1e1e2e"},"gitsigns":{"add":"#abe9b3","remove":"#f28fad","change":"#fae3b0"},"border":"#96cdfb","dimmed":{"subtle":"#575268","inactive":"#6e6c7e"},"heading":{"h2":"#0","h1":"#f5c2e7"},"cyan":"#B5E8E0","scheme-name":"catppuccin","match":"#d9e0ee","magenta":"#DDB6F2","search_result":{"fg":"#f5c2e7","telescope":"#96cdfb","bg":"#575268"},"bg":{"base":"#1e1e2e","selected":"#302d41","alt":"#1a1826"},"syntax":{"operator":"#89dceb","todo":{"fg":"#1e1e2e","bg":"#fae3b0"},"property":"#fae3b0","statement":"#ddb6f2","tag":"#f8bd96","punctuation":"#988ba2","keyword":"#f28fad","parameter":"#f5e0dc","struct":"#fae3b0","type":"#fae3b0","field":"#f5e0dc","number":"#f8bd96","preproc":"#f5c2e7","string":"#abe9b3","variable":"#d9e0ee","comment":"#6e6c7e","include":"#f5c2e7","constructor":"#c9cbff","function":"#96cdfb","constant":"#f8bd96","conditional":"#ddb6f2"},"built_in":{"type":"#fae3b0","keyword":"#e8a2af","function":"#f8bd96","constant":"#c9cbff","variable":"#b5e8e0"},"inc_search":{"bg":"#f5c2e7","fg":"#575268"},"blue":"#96CDFB"}