{"blue":"#96CDFB","cyan":"#B5E8E0","bg":{"alt":"#1a1826","selected":"#302d41","base":"#1e1e2e"},"orange":"#FAE3B0","gitsigns":{"remove":"#f28fad","change":"#fae3b0","add":"#abe9b3"},"fg":"#d9e0ee","yellow":"#FAE3B0","scheme-name":"catppuccin","match":"#d9e0ee","search_result":{"telescope":"#96cdfb","fg":"#f5c2e7","bg":"#575268"},"border":"#96cdfb","uri":"#f5e0dc","diff":{"remove":"#1e1e2e","change":"#1e1e2e","text":"#1e1e2e","add":"#1e1e2e"},"built_in":{"function":"#f8bd96","type":"#fae3b0","constant":"#c9cbff","keyword":"#e8a2af","variable":"#b5e8e0"},"pum":{"sel":{"fg":"#d9e0ee","bg":"#575268"},"fg":"#c3bac6","thumb":"#6e6c7e","sbar":"#575268","bg":"#302d41"},"syntax":{"constructor":"#c9cbff","property":"#fae3b0","punctuation":"#988ba2","include":"#f5c2e7","field":"#f5e0dc","function":"#96cdfb","string":"#abe9b3","operator":"#89dceb","todo":{"bg":"#fae3b0","fg":"#1e1e2e"},"statement":"#ddb6f2","tag":"#f8bd96","number":"#f8bd96","parameter":"#f5e0dc","comment":"#6e6c7e","type":"#fae3b0","conditional":"#ddb6f2","constant":"#f8bd96","variable":"#d9e0ee","keyword":"#f28fad","preproc":"#f5c2e7","struct":"#fae3b0"},"heading":{"h2":"#0","h1":"#f5c2e7"},"green":"#ABE9B3","inc_search":{"fg":"#575268","bg":"#f5c2e7"},"accent":"#f5c2e7","magenta":"#DDB6F2","dimmed":{"subtle":"#575268","inactive":"#6e6c7e"},"diagnostic":{"error":"#f28fad","info":"#89dceb","hint":"#f5e0dc","warn":"#fae3b0"},"cursorlinenr":"#abe9b3"}