{"fg":"#d9e0ee","pum":{"sbar":"#575268","fg":"#c3bac6","sel":{"bg":"#575268","fg":"#d9e0ee"},"thumb":"#6e6c7e","bg":"#302d41"},"cyan":"#B5E8E0","diagnostic":{"warn":"#fae3b0","error":"#f28fad","hint":"#f5e0dc","info":"#89dceb"},"uri":"#f5e0dc","dimmed":{"subtle":"#575268","inactive":"#6e6c7e"},"magenta":"#DDB6F2","accent":"#f5c2e7","cursorlinenr":"#abe9b3","bg":{"alt":"#1a1826","selected":"#302d41","base":"#1e1e2e"},"search_result":{"fg":"#f5c2e7","telescope":"#96cdfb","bg":"#575268"},"diff":{"change":"#1e1e2e","remove":"#1e1e2e","text":"#1e1e2e","add":"#1e1e2e"},"scheme-name":"catppuccin","yellow":"#FAE3B0","gitsigns":{"change":"#fae3b0","remove":"#f28fad","add":"#abe9b3"},"border":"#96cdfb","green":"#ABE9B3","heading":{"h1":"#f5c2e7","h2":"#0"},"syntax":{"function":"#96cdfb","tag":"#f8bd96","type":"#fae3b0","variable":"#d9e0ee","property":"#fae3b0","number":"#f8bd96","punctuation":"#988ba2","keyword":"#f28fad","constructor":"#c9cbff","include":"#f5c2e7","statement":"#ddb6f2","operator":"#89dceb","preproc":"#f5c2e7","field":"#f5e0dc","conditional":"#ddb6f2","struct":"#fae3b0","parameter":"#f5e0dc","string":"#abe9b3","todo":{"fg":"#1e1e2e","bg":"#fae3b0"},"constant":"#f8bd96","comment":"#6e6c7e"},"blue":"#96CDFB","built_in":{"variable":"#b5e8e0","function":"#f8bd96","keyword":"#e8a2af","constant":"#c9cbff","type":"#fae3b0"},"match":"#d9e0ee","inc_search":{"bg":"#f5c2e7","fg":"#575268"},"orange":"#FAE3B0"}