{"green":"#69ff94","gitsigns":{"text":"#BD93F9","remove":"#E95678","add":"#69ff94","change":"#F1FA8C"},"border":"#BD93F9","orange":"#FFB86C","uri":"#ffb86c","cyan":"#0088cc","accent":"#8be9fd","yellow":"#F1FA8C","diagnostic":{"error":"#E95678","info":"#69ff94","warn":"#F1FA8C","hint":"#BD93F9"},"heading":{"h2":"#BD93F9","h1":"#BD93F9"},"search_result":{"fg":"#3a3c4e","telescope":"#8be9fd","bg":"#8be9fd"},"inc_search":{"fg":"#3a3c4e","bg":"#bd93f9"},"built_in":{"variable":"#8be9fd","constant":"#bd93f9","function":"#8be9fd","keyword":"#ff92df","type":"#8be9fd"},"scheme-name":"dracula","syntax":{"function":"#69ff94","punctuation":"#f7f7fb","identifier":"#ffb86c","type":"#8be9fd","number":"#bd93f9","operator":"#e9e9f4","struct":"#ff92df","include":"#69ff94","constructor":"#8be9fd","property":"#ffb86c","field":"#8be9fd","conditional":"#ff92df","todo":{"fg":"#8be9fd","bg":"#3a3c4e"},"string":"#ffffa5","variable":"#e9e9f4","comment":"#6272a4","constant":"#bd93f9","statement":"#ffb86c","preproc":"#8be9fd","parameter":"#ffb86c","keyword":"#ff92df"},"pum":{"fg":"#6272a4","thumb":"#b389ef","bg":"#373844","sel":{"bg":"#b389ef","fg":"#e9e9f4"},"sbar":"#44475a"},"dimmed":{"inactive":"#6272a4","subtle":"#666771"},"fg":"#F8F8F2","red":"#E95678","match":"#6272a4","blue":"#BD93F9","bg":{"base":"#282a36","selected":"#44475a","alt":"#232531"},"diff":{"text":"#BD93F9","remove":"#E95678","add":"#69ff94","change":"#F1FA8C"},"directory":"#BD93F9","magenta":"#BD93F9"}