{"match":"#58a6ff","cyan":"#39c5cf","diagnostic":{"warn":"#f0883e","error":"#f85149","hint":"#eeeeb3","info":"#75beff"},"syntax":{"type":"#d69a00","statement":"#d69a00","variable":"#9b4215","operator":"#d69a00","struct":"#d69a00","property":"#d2a8ff","comment":"#8b949e","function":"#d2a8ff","preproc":"#d69a00","keyword":"#d69a00","tag":"#83d4ff","string":"#a5d6ff","punctuation":"#c9d1d9","field":"#c9d1d9","include":"#d69a00","number":"#79b8ff","conditional":"#d69a00","todo":{"bg":"#d29922","fg":"#d1117"},"constant":"#79b8ff","constructor":"#9b4215","parameter":"#c9d1d9"},"pum":{"sbar":"#161b22","bg":"#161b22","sel":{"bg":"#5e94c5","fg":"#161b22"},"thumb":"#31373d","fg":"#c9d1d9"},"yellow":"#d29922","uri":"#0","cursorlinenr":"#c9d1d9","bg":{"selected":"#161b22","alt":"#d1117","base":"#d1117"},"heading":{"h1":"#0","h2":"#0"},"fg":"#c9d1d9","diff":{"add":"#244032","change":"#341a00","text":"#0","remove":"#462c32"},"blue":"#58a6ff","built_in":{"type":"#d69a00","function":"#9b4215","variable":"#9b4215","constant":"#9b4215","keyword":"#d69a00"},"gitsigns":{"add":"#244032","change":"#341a00","text":"#0","remove":"#462c32"},"border":"#b3b1ad","dimmed":{"inactive":"#d1117","subtle":"#d1117"},"inc_search":{"bg":"#2c2b1c","fg":"#0"},"orange":"#e3b341","search_result":{"bg":"#2c2b1c","fg":"#0","telescope":"#79b8ff"},"scheme-name":"github_dark_colorblind","green":"#3fb950","magenta":"#bc8cff","accent":"#9b4215"}