{"orange":"#ffea7f","fg":"#c9d1d9","diff":{"add":"#244032","change":"#341a00","text":"#0","remove":"#462c32"},"syntax":{"property":"#b392f0","struct":"#f97583","conditional":"#f97583","keyword":"#f97583","todo":{"bg":"#ffea7f","fg":"#24292e"},"punctuation":"#c9d1d9","type":"#f97583","include":"#f97583","constant":"#79b8ff","parameter":"#e1e4e8","constructor":"#79b8ff","string":"#9ecbff","number":"#79b8ff","preproc":"#f97583","variable":"#79b8ff","comment":"#6a737d","statement":"#f97583","operator":"#f97583","tag":"#85e89d","function":"#b392f0","field":"#c9d1d9"},"pum":{"sbar":"#1f2428","fg":"#c9d1d9","thumb":"#32383e","sel":{"bg":"#6494cb","fg":"#1f2428"},"bg":"#1f2428"},"border":"#c9d1d9","bg":{"alt":"#24292e","base":"#24292e","selected":"#2c313a"},"uri":"#0","gitsigns":{"add":"#244032","change":"#341a00","text":"#0","remove":"#462c32"},"heading":{"h1":"#0","h2":"#0"},"scheme-name":"github_dark","cyan":"#39c5cf","built_in":{"keyword":"#f97583","variable":"#79b8ff","type":"#f97583","constant":"#79b8ff","function":"#79b8ff"},"match":"#2188ff","cursorlinenr":"#e1e4e8","search_result":{"telescope":"#79b8ff","fg":"#0","bg":"#404030"},"yellow":"#ffea7f","diagnostic":{"hint":"#eeeeb3","error":"#f97583","warn":"#cca700","info":"#75beff"},"green":"#34d058","dimmed":{"inactive":"#666666","subtle":"#666666"},"blue":"#2188ff","accent":"#79b8ff","inc_search":{"bg":"#404030","fg":"#0"},"magenta":"#b392f0"}