{"fg":"#c9d1d9","magenta":"#bc8cff","pum":{"sbar":"#161b22","sel":{"fg":"#161b22","bg":"#5e94c5"},"fg":"#c9d1d9","thumb":"#31373d","bg":"#161b22"},"diagnostic":{"info":"#75beff","error":"#f85149","hint":"#eeeeb3","warn":"#f0883e"},"dimmed":{"subtle":"#d1117","inactive":"#d1117"},"search_result":{"bg":"#2c2b1c","telescope":"#79b8ff","fg":"#0"},"uri":"#0","gitsigns":{"remove":"#462c32","change":"#341a00","text":"#0","add":"#244032"},"orange":"#e3b341","diff":{"remove":"#462c32","change":"#341a00","text":"#0","add":"#244032"},"built_in":{"variable":"#9b4215","constant":"#9b4215","keyword":"#d69a00","function":"#9b4215","type":"#d69a00"},"scheme-name":"github_dark_colorblind","blue":"#58a6ff","syntax":{"constructor":"#9b4215","property":"#d2a8ff","keyword":"#d69a00","number":"#79b8ff","punctuation":"#c9d1d9","todo":{"fg":"#d1117","bg":"#d29922"},"type":"#d69a00","struct":"#d69a00","variable":"#9b4215","preproc":"#d69a00","include":"#d69a00","comment":"#8b949e","function":"#d2a8ff","tag":"#83d4ff","operator":"#d69a00","string":"#a5d6ff","constant":"#79b8ff","conditional":"#d69a00","statement":"#d69a00","parameter":"#c9d1d9","field":"#c9d1d9"},"inc_search":{"fg":"#0","bg":"#2c2b1c"},"yellow":"#d29922","match":"#58a6ff","accent":"#9b4215","border":"#b3b1ad","cursorlinenr":"#c9d1d9","cyan":"#39c5cf","green":"#3fb950","heading":{"h2":"#0","h1":"#0"},"bg":{"base":"#d1117","selected":"#161b22","alt":"#d1117"}}