{"dimmed":{"subtle":"#d1117","inactive":"#d1117"},"green":"#3fb950","cursorlinenr":"#c9d1d9","match":"#58a6ff","border":"#b3b1ad","diagnostic":{"error":"#f85149","warn":"#f0883e","info":"#75beff","hint":"#eeeeb3"},"gitsigns":{"change":"#341a00","text":"#0","remove":"#462c32","add":"#244032"},"syntax":{"number":"#79b8ff","statement":"#d69a00","todo":{"fg":"#d1117","bg":"#d29922"},"property":"#d2a8ff","comment":"#8b949e","variable":"#9b4215","preproc":"#d69a00","type":"#d69a00","string":"#a5d6ff","tag":"#83d4ff","punctuation":"#c9d1d9","operator":"#d69a00","keyword":"#d69a00","struct":"#d69a00","constructor":"#9b4215","function":"#d2a8ff","conditional":"#d69a00","field":"#c9d1d9","constant":"#79b8ff","parameter":"#c9d1d9","include":"#d69a00"},"orange":"#e3b341","cyan":"#39c5cf","accent":"#9b4215","inc_search":{"fg":"#0","bg":"#2c2b1c"},"uri":"#0","bg":{"base":"#d1117","selected":"#161b22","alt":"#d1117"},"fg":"#c9d1d9","heading":{"h1":"#0","h2":"#0"},"blue":"#58a6ff","search_result":{"telescope":"#79b8ff","fg":"#0","bg":"#2c2b1c"},"yellow":"#d29922","built_in":{"variable":"#9b4215","type":"#d69a00","function":"#9b4215","constant":"#9b4215","keyword":"#d69a00"},"pum":{"fg":"#c9d1d9","sel":{"fg":"#161b22","bg":"#5e94c5"},"thumb":"#31373d","bg":"#161b22","sbar":"#161b22"},"diff":{"change":"#341a00","text":"#0","remove":"#462c32","add":"#244032"},"magenta":"#bc8cff","scheme-name":"github_dark_colorblind"}