{"yellow":"#d8a657","diff":{"remove":"#402120","change":"#e363e","text":"#7daea3","add":"#34381b"},"orange":"#d8a657","match":"#a9b665","dimmed":{"inactive":"#5a524c","subtle":"#928374"},"fg":"#d4be98","green":"#a9b665","magenta":"#d3869b","blue":"#7daea3","gitsigns":{"remove":"#402120","change":"#e363e","text":"#7daea3","add":"#34381b"},"cyan":"#89b482","scheme-name":"gruvbox-material-dark-medium","inc_search":{"fg":"#282828","bg":"#ea6962"},"search_result":{"telescope":"#a9b665","fg":"#282828","bg":"#a9b665"},"built_in":{"variable":"#7daea3","keyword":"#ea6962","type":"#d8a657","function":"#a9b665","constant":"#7daea3"},"accent":"#d8a657","cursorlinenr":"#928374","bg":{"alt":"#45403d","selected":"#32302f","base":"#282828"},"syntax":{"parameter":"#d4be98","variable":"#d4be98","tag":"#e78a4e","punctuation":"#d4be98","statement":"#ea6962","operator":"#e78a4e","property":"#d4be98","comment":"#928374","todo":{"fg":"#d3869b","bg":"#0"},"function":"#a9b665","field":"#a9b665","preproc":"#d3869b","keyword":"#ea6962","type":"#d8a657","conditional":"#ea6962","constructor":"#a9b665","constant":"#d4be98","include":"#d3869b","number":"#d3869b","string":"#89b482","struct":"#e78a4e"},"uri":"#7daea3","pum":{"sel":{"fg":"#45403d","bg":"#a89984"},"fg":"#ddc7a1","thumb":"#7c6f64","bg":"#45403d","sbar":"#45403d"},"border":"#5a524c","diagnostic":{"error":"#0","warn":"#0","hint":"#0","info":"#0"},"heading":{"h2":"#0","h1":"#ea6962"}}