{"blue":"#4c66e6","inc_search":{"fg":"#f4f0f4","bg":"#ca80ff"},"diff":{"change":"#ffff80","add":"#8fef97","text":"#8f9fef","delete":"#ff3333"},"scheme-name":"kurai","pum":{"fg":"#e9e2e9","sel":{"bg":"#272428","fg":"#e9e2e9"},"sbar":"#272428","bg":"#1a181b","thumb":"#e9e2e9"},"border":"#343036","accent":"#9500ff","bg":{"alt":"#1a181b","selected":"#343036","base":"#272428"},"gitsigns":{"change":"#ffff80","add":"#8fef97","text":"#8f9fef","delete":"#ff3333"},"remaps":{"plugins":{"telescope":{"TelescopeResultsTitle":{"fg":"#1a181b","bg":"#4c66e6"},"TelescopeSelectionCaret":{"fg":"#661fad","bg":"#1a181b"},"TelescopePromptBorder":{"fg":"#e9e2e9","bg":"#1a181b"},"TelescopeSelection":{"bg":"#343036"},"TelescopeBorder":{"fg":"#1a181b","bg":"#1a181b"},"TelescopePromptNormal":{"fg":"#e9e2e9","bg":"#1a181b"},"TelescopePromptTitle":{"fg":"#1a181b","bg":"#ffff80"},"TelescopeResultsNormal":{"bg":"#1a181b"},"TelescopeMatching":{"bg":"#8f9fef"},"TelescopePromptPrefix":{"fg":"#ff9933"},"TelescopePreviewNormal":{"bg":"#1a181b"},"TelescopePromptCounter":{"fg":"#9500ff"},"TelescopePreviewTitle":{"fg":"#1a181b","bg":"#8fef97"}},"cmp":{"CmpItemMenu":{"fg":"#4ce659"},"CmpItemAbbrMatch":{"fg":"#9500ff"},"CmpItemAbbrDeprecated":{"fg":"#ff3333"},"CmpItemAbbrMatchFuzzy":{"fg":"#9500ff"}}}},"diagnostic":{"hint":"#4c66e6","warn":"#ffff33","error":"#ff3333","info":"#9500ff"},"match":"#4c66e6","dimmed":{"inactive":"#343036","subtle":"#343036"},"built_in":{"keyword":"#ff8080","constant":"#ffff80","variable":"#ff8080","function":"#8f9fef"},"syntax":{"statement":"#ca80ff","keyword":"#ca80ff","operator":"#ca80ff","punctuation":"#68616b","struct":"#4c66e6","constructor":"#7f20df","string":"#ffff80","field":"#8f9fef","comment":"#68616b","include":"#ffbf80","parameter":"#ca80ff","conditional":"#ca80ff","constant":"#ffff33","property":"#4c66e6","type":"#8fef97","number":"#ff8080","preproc":"#ffff80","todo":{"fg":"#f4f0f4","bg":"#aa33ff"},"variable":"#e9e2e9","function":"#8f9fef"},"orange":"#ff9933","green":"#4ce659","cyan":"#8f9fef","heading":{"h1":"#8fef97","h2":"#4ce659"},"search_result":{"bg":"#8f9fef","fg":"#e9e2e9","telescope":"#e9e2e9"},"red":"#ff3333","magenta":"#9500ff","yellow":"#ffff80","fg":"#e9e2e9","uri":"#661fad"}