{"built_in":{"function":"#a1efe4","constant":"#fd971f","type":"#f4bf75","keyword":"#ae81ff","variable":"#a1efe4"},"orange":"#fca2aa","inc_search":{"fg":"#383830","bg":"#fd971f"},"red":"#d47d85","green":"#A3BE8C","syntax":{"struct":"#ae81ff","keyword":"#ae81ff","variable":"#f8f8f2","preproc":"#f4bf75","field":"#f4bf75","include":"#66d9ef","todo":{"fg":"#f4bf75","bg":"#383830"},"comment":"#75715e","function":"#66d9ef","statement":"#f92672","type":"#f4bf75","constructor":"#a1efe4","conditional":"#ae81ff","parameter":"#f92672","number":"#fd971f","constant":"#fd971f","property":"#f92672","operator":"#f8f8f2","punctuation":"#cc6633","identifier":"#f92672","string":"#a6e22e"},"cyan":"#519ABA","accent":"#a1efe4","dimmed":{"inactive":"#75715e","subtle":"#565c64"},"yellow":"#e7c787","border":"#61afef","diff":{"text":"#61afef","change":"#e7c787","add":"#A3BE8C","remove":"#d47d85"},"gitsigns":{"text":"#61afef","change":"#e7c787","add":"#A3BE8C","remove":"#d47d85"},"scheme-name":"monokai","uri":"#f92672","heading":{"h1":"#61afef","h2":"#61afef"},"search_result":{"fg":"#383830","telescope":"#f4bf75","bg":"#f4bf75"},"blue":"#61afef","pum":{"fg":"#f5f4f1","thumb":"#81A1C1","bg":"#282c34","sel":{"bg":"#A3BE8C","fg":"#f8f8f2"},"sbar":"#353b45"},"fg":"#abb2bf","match":"#f5f4f1","bg":{"base":"#272822","selected":"#49483e","alt":"#1b1f27"},"diagnostic":{"warn":"#e7c787","hint":"#b4bbc8","info":"#A3BE8C","error":"#d47d85"},"directory":"#61afef","magenta":"#c882e7"}