{"orange":"#c8916d","diff":{"remove":"#a67476","text":"#5a6986","add":"#8aa387","change":"#ccb89c"},"search_result":{"fg":"#222329","bg":"#d4ae80","telescope":"#d4ae80"},"uri":"#b8aad9","fg":"#f1ebd1","bg":{"selected":"#2c2d33","base":"#18191f","alt":"#15161c"},"red":"#a67476","dimmed":{"subtle":"#43444a","inactive":"#3c3d43"},"yellow":"#ccb89c","directory":"#90a0a0","scheme-name":"nightlamp","built_in":{"constant":"#b17f81","keyword":"#8896ae","variable":"#9ba292","type":"#d4ae80","function":"#9ba292"},"green":"#8aa387","syntax":{"property":"#b8aad9","preproc":"#d4ae80","parameter":"#b8aad9","struct":"#8896ae","function":"#c495a2","statement":"#b8aad9","variable":"#cbc0ab","constructor":"#9ba292","operator":"#cbc0ab","field":"#d4ae80","include":"#c495a2","identifier":"#b8aad9","constant":"#b17f81","comment":"#3c3d43","punctuation":"#d0d0c7","number":"#b17f81","todo":{"fg":"#d4ae80","bg":"#222329"},"keyword":"#8896ae","string":"#8aa387","conditional":"#8896ae"},"heading":{"h2":"#5a6986","h1":"#5a6986"},"pum":{"fg":"#e0d6bd","thumb":"#8d9bb3","bg":"#222329","sel":{"bg":"#8aa387","fg":"#cbc0ab"},"sbar":"#28292f"},"match":"#e0d6bd","inc_search":{"fg":"#222329","bg":"#b17f81"},"diagnostic":{"hint":"#b8aad9","error":"#a67476","info":"#8aa387","warn":"#ccb89c"},"border":"#5a6986","blue":"#5a6986","accent":"#9ba292","cyan":"#7aacaa","magenta":"#a99bca","gitsigns":{"remove":"#a67476","text":"#5a6986","add":"#8aa387","change":"#ccb89c"}}