{"red":"#d94848","green":"#98C379","diagnostic":{"error":"#d94848","hint":"#5d8ac2","warn":"#d4d198","info":"#d94848"},"search_result":{"telescope":"#5d8ac2","bg":"#2e3440","fg":"#c487b9"},"match":"#E5E9F0","gitsigns":{"change":"#d4d198","add":"#98C379","text":"#5d8ac2","remove":"#d94848"},"accent":"#5d8ac2","magenta":"#c487b9","heading":{"h2":"#d94848","h1":"#d94848"},"blue":"#5d8ac2","pum":{"sel":{"bg":"#3E4452"},"sbar":"#3E4452","bg":"#2e3440","thumb":"#E5E9F0","fg":"#3B4252"},"orange":"#d08770","uri":"#d94848","border":"#5d8ac2","built_in":{"variable":"#8fc6e3","type":"#d4d198","keyword":"#5d8ac2","constant":"#5d8ac2","function":"#d4d198"},"syntax":{"operator":"#5d8ac2","field":"#8fc6e3","parameter":"#8fc6e3","constructor":"#84D9AA","preproc":"#d94848","struct":"#d94848","punctuation":"#5d8ac2","constant":"#5d8ac2","property":"#d4d198","keyword":"#5d8ac2","todo":{"bg":"#d4d198","fg":"#2e3440"},"variable":"#d94848","number":"#B4CDA8","comment":"#699856","type":"#d94848","string":"#A3BE8C","include":"#d94848","function":"#5d8ac2"},"scheme-name":"papa_dark","dimmed":{"inactive":"#4C566A","subtle":"#4c566a"},"bg":{"alt":"#2b2e36","selected":"#3B4252","base":"#2e3440"},"cyan":"#4EC9B0","yellow":"#d4d198","diff":{"change":"#d4d198","add":"#98C379","text":"#5d8ac2","remove":"#d94848"},"remaps":{"plugins":{"telescope":{"TelescopeSelection":{"bg":"#434c5e"},"TelescopeResultsTitle":{"bg":"#5d8ac2","fg":"#2b2e36"},"TelescopeResultsNormal":{"bg":"#2b2e36"},"TelescopeSelectionCaret":{"bg":"#2b2e36","fg":"#2b2e36"},"TelescopeBorder":{"bg":"#2b2e36","fg":"#2b2e36"},"TelescopePreviewNormal":{"bg":"#2b2e36"},"TelescopePromptPrefix":{"bg":"#2b2e36","fg":"#5d8ac2"},"TelescopePreviewTitle":{"bg":"#98C379","fg":"#2b2e36"},"TelescopePromptNormal":{"bg":"#2b2e36","fg":"#E5E9F0"},"TelescopePromptTitle":{"bg":"#d4d198","fg":"#2b2e36"},"TelescopePromptBorder":{"bg":"#2b2e36","fg":"#2e3440"},"TelescopeMatching":{"fg":"#5d8ac2"}},"cmp":{"CmpItemAbbrMatch":{"fg":"#8fc6e3"},"CmpItemKind":{"fg":"#5d8ac2"},"CmpItemKindVariable":{"fg":"#8fc6e3"},"CmpItemMenu":{"fg":"#5d8ac2"},"CmpItemAbbr":{"fg":"#E5E9F0"}},"trouble":{"TroubleSignWarning":{"fg":"#d4d198"},"TroubleSignError":{"fg":"#d94848"}},"gitsigns":{"GitSignsDelete":{"fg":"#d94848"},"GitSignsChange":{"bg":"#2e3440","fg":"#d4d198"}},"treesitter":{"@error":{"link":"Error"},"TSProperty":{"link":"TSField"},"TSConstant":{"link":"Constant"},"TSCharacter":{"link":"Character"},"@punctuation.bracket":{"fg":"#5d8ac2"},"@keyword.function":{"link":"Keyword"},"@character":{"link":"Character"},"TSTypeBuiltin":{"fg":"#5d8ac2"},"@field":{"fg":"#8fc6e3"},"TSVariable":{"link":"TSField"},"@property":{"link":"TSField"},"@function.macro":{"link":"Function"},"TSFuncMacro":{"link":"Function"},"TSKeywordFunction":{"link":"Keyword"},"@variable":{"link":"TSField"},"TSInclude":{"link":"Keyword"},"TSLabel":{"link":"String"},"TSConditional":{"link":"Keyword"},"@label":{"link":"String"},"TSNamespace":{"fg":"#4EC9B0"},"TSKeyword":{"fg":"#5d8ac2"},"TSTitle":{"link":"String"},"TSConstructor":{"fg":"#5d8ac2"},"@include":{"link":"Keyword"},"TSFuncBuiltin":{"link":"Function"},"TSTag":{"link":"Keyword"},"@keyword":{"fg":"#5d8ac2"},"@tag":{"link":"Keyword"},"TSVariableBuiltin":{"link":"Keyword"},"@variable.builtin":{"link":"Keyword"},"TSConstBuiltin":{"link":"Keyword"},"@constant.builtin":{"link":"Keyword"},"@conditional":{"link":"Keyword"},"@boolean":{"link":"Boolean"},"@constant":{"link":"Constant"},"TSMethod":{"link":"Function"},"@method":{"link":"Function"},"@function":{"link":"Function"},"TSType":{"fg":"#4EC9B0"},"@type":{"fg":"#4EC9B0"},"TSPunctBracket":{"fg":"#5d8ac2"},"TSField":{"fg":"#8fc6e3"},"@text.title":{"link":"String"},"TSFunction":{"link":"Function"},"TSBoolean":{"link":"Boolean"},"@namespace":{"fg":"#4EC9B0"},"@type.builtin":{"fg":"#5d8ac2"},"@constructor":{"fg":"#5d8ac2"},"@function.builtin":{"link":"Function"},"TSError":{"link":"Error"}},"nvim_tree":{"NvimTreeGitDirty":{"fg":"#d4d198"},"NvimTreeFileDeleted":{"fg":"#d94848"},"NvimTreeGitDeleted":{"fg":"#d94848"},"NvimTreeRootFolder":{"fg":"#8fc6e3"}},"lsp":{"DiagnosticUnderlineWarn":{"style":"underline","sp":"#d4d198","fg":"NONE"},"DiagnosticUnderlineHint":{"style":"underline","sp":"#8fc6e3","fg":"NONE"}}},"langs":{"md":{"markdownCode":{"fg":"#A3BE8C"}}},"base":{"Boolean":{"link":"Constant"},"Directory":{"fg":"#5d8ac2"},"Whitespace":{"fg":"#E5E9F0"},"TabLineSel":{"fg":"#E5E9F0"},"EndOfBuffer":{"fg":"#2e3440"},"Special":{"fg":"#5d8ac2"},"Type":{"fg":"#5d8ac2"},"WarningMsg":{"fg":"#d4d198"},"ErrorMsg":{"bg":"#d94848","fg":"#E5E9F0"},"Search":{"bg":"#5d8ac2"},"ColorColumn":{"fg":"#d94848"},"NonText":{"fg":"#5d8ac2"},"FloatBorder":{"fg":"#E5E9F0"},"MatchParen":{"bg":"#5d8ac2","fg":"#E5E9F0"},"Constant":{"fg":"#5d8ac2"},"Folded":{"fg":"#699856"},"PreProc":{"link":"Statement"},"Statement":{"fg":"#5d8ac2"},"IncSearch":{"bg":"#699856","fg":"#d4d198"},"Identifier":{"fg":"#8fc6e3"},"Float":{"link":"Number"},"Normal":{"bg":"#2e3440","fg":"#E5E9F0"},"Number":{"fg":"#B4CDA8"},"Character":{"link":"String"},"VertSplit":{"bg":"#2e3440","fg":"#373e4a"},"CursorLineNr":{"fg":"#E5E9F0"},"Visual":{"bg":"#3E4452"},"CursorLine":{"bg":"#3B4252"},"TabLineFill":{"bg":"#2e3440"},"TabLine":{"fg":"#699856"},"Function":{"fg":"#d4d198"}}}}