{"remaps":{"langs":{"md":{"markdownCode":{"fg":"#A3BE8C"}}},"base":{"CursorLineNr":{"fg":"#E5E9F0"},"EndOfBuffer":{"fg":"#2e3440"},"Constant":{"fg":"#5d8ac2"},"PreProc":{"link":"Statement"},"Normal":{"bg":"#2e3440","fg":"#E5E9F0"},"TabLineSel":{"fg":"#E5E9F0"},"Directory":{"fg":"#5d8ac2"},"Function":{"fg":"#d4d198"},"Type":{"fg":"#5d8ac2"},"WarningMsg":{"fg":"#d4d198"},"NonText":{"fg":"#5d8ac2"},"ErrorMsg":{"bg":"#d94848","fg":"#E5E9F0"},"Statement":{"fg":"#5d8ac2"},"Identifier":{"fg":"#8fc6e3"},"Float":{"link":"Number"},"Boolean":{"link":"Constant"},"ColorColumn":{"fg":"#d94848"},"CursorLine":{"bg":"#3B4252"},"Whitespace":{"fg":"#E5E9F0"},"VertSplit":{"bg":"#2e3440","fg":"#373e4a"},"Number":{"fg":"#B4CDA8"},"Visual":{"bg":"#3E4452"},"TabLine":{"fg":"#699856"},"FloatBorder":{"fg":"#E5E9F0"},"Character":{"link":"String"},"TabLineFill":{"bg":"#2e3440"},"IncSearch":{"bg":"#699856","fg":"#d4d198"},"Special":{"fg":"#5d8ac2"},"Search":{"bg":"#5d8ac2"},"MatchParen":{"bg":"#5d8ac2","fg":"#E5E9F0"},"Folded":{"fg":"#699856"}},"plugins":{"cmp":{"CmpItemKindVariable":{"fg":"#8fc6e3"},"CmpItemAbbr":{"fg":"#E5E9F0"},"CmpItemAbbrMatch":{"fg":"#8fc6e3"},"CmpItemMenu":{"fg":"#5d8ac2"},"CmpItemKind":{"fg":"#5d8ac2"}},"gitsigns":{"GitSignsChange":{"bg":"#2e3440","fg":"#d4d198"},"GitSignsDelete":{"fg":"#d94848"}},"lsp":{"DiagnosticUnderlineHint":{"sp":"#8fc6e3","style":"underline","fg":"NONE"},"DiagnosticUnderlineWarn":{"sp":"#d4d198","style":"underline","fg":"NONE"}},"telescope":{"TelescopeBorder":{"bg":"#2b2e36","fg":"#2b2e36"},"TelescopePreviewNormal":{"bg":"#2b2e36"},"TelescopeResultsTitle":{"bg":"#5d8ac2","fg":"#2b2e36"},"TelescopePromptBorder":{"bg":"#2b2e36","fg":"#2e3440"},"TelescopePromptPrefix":{"bg":"#2b2e36","fg":"#5d8ac2"},"TelescopePreviewTitle":{"bg":"#98C379","fg":"#2b2e36"},"TelescopeSelection":{"bg":"#434c5e"},"TelescopePromptTitle":{"bg":"#d4d198","fg":"#2b2e36"},"TelescopeMatching":{"fg":"#5d8ac2"},"TelescopeResultsNormal":{"bg":"#2b2e36"},"TelescopeSelectionCaret":{"bg":"#2b2e36","fg":"#2b2e36"},"TelescopePromptNormal":{"bg":"#2b2e36","fg":"#E5E9F0"}},"nvim_tree":{"NvimTreeGitDirty":{"fg":"#d4d198"},"NvimTreeRootFolder":{"fg":"#8fc6e3"},"NvimTreeGitDeleted":{"fg":"#d94848"},"NvimTreeFileDeleted":{"fg":"#d94848"}},"treesitter":{"@text.title":{"link":"String"},"TSFunction":{"link":"Function"},"TSInclude":{"link":"Keyword"},"@constant":{"link":"Constant"},"@keyword.function":{"link":"Keyword"},"@function.macro":{"link":"Function"},"@character":{"link":"Character"},"@method":{"link":"Function"},"TSVariable":{"link":"TSField"},"TSField":{"fg":"#8fc6e3"},"TSMethod":{"link":"Function"},"@variable.builtin":{"link":"Keyword"},"@namespace":{"fg":"#4EC9B0"},"@function.builtin":{"link":"Function"},"TSProperty":{"link":"TSField"},"TSBoolean":{"link":"Boolean"},"@variable":{"link":"TSField"},"TSKeyword":{"fg":"#5d8ac2"},"TSType":{"fg":"#4EC9B0"},"@function":{"link":"Function"},"@constructor":{"fg":"#5d8ac2"},"TSConstructor":{"fg":"#5d8ac2"},"@field":{"fg":"#8fc6e3"},"TSTitle":{"link":"String"},"TSCharacter":{"link":"Character"},"@include":{"link":"Keyword"},"TSTag":{"link":"Keyword"},"@type.builtin":{"fg":"#5d8ac2"},"@tag":{"link":"Keyword"},"TSError":{"link":"Error"},"@error":{"link":"Error"},"TSPunctBracket":{"fg":"#5d8ac2"},"TSVariableBuiltin":{"link":"Keyword"},"@property":{"link":"TSField"},"TSNamespace":{"fg":"#4EC9B0"},"TSConstBuiltin":{"link":"Keyword"},"@label":{"link":"String"},"TSConditional":{"link":"Keyword"},"TSConstant":{"link":"Constant"},"TSFuncMacro":{"link":"Function"},"TSFuncBuiltin":{"link":"Function"},"TSTypeBuiltin":{"fg":"#5d8ac2"},"@keyword":{"fg":"#5d8ac2"},"@constant.builtin":{"link":"Keyword"},"@punctuation.bracket":{"fg":"#5d8ac2"},"TSLabel":{"link":"String"},"@type":{"fg":"#4EC9B0"},"@conditional":{"link":"Keyword"},"TSKeywordFunction":{"link":"Keyword"},"@boolean":{"link":"Boolean"}},"trouble":{"TroubleSignWarning":{"fg":"#d4d198"},"TroubleSignError":{"fg":"#d94848"}}}},"blue":"#5d8ac2","magenta":"#c487b9","red":"#d94848","yellow":"#d4d198","green":"#98C379","bg":{"alt":"#2b2e36","base":"#2e3440","selected":"#3B4252"},"diff":{"add":"#98C379","remove":"#d94848","text":"#5d8ac2","change":"#d4d198"},"cyan":"#4EC9B0","match":"#E5E9F0","gitsigns":{"add":"#98C379","remove":"#d94848","text":"#5d8ac2","change":"#d4d198"},"orange":"#d08770","scheme-name":"papa_dark","heading":{"h2":"#d94848","h1":"#d94848"},"pum":{"sbar":"#3E4452","fg":"#3B4252","thumb":"#E5E9F0","sel":{"bg":"#3E4452"},"bg":"#2e3440"},"dimmed":{"subtle":"#4c566a","inactive":"#4C566A"},"uri":"#d94848","diagnostic":{"hint":"#5d8ac2","error":"#d94848","info":"#d94848","warn":"#d4d198"},"search_result":{"bg":"#2e3440","telescope":"#5d8ac2","fg":"#c487b9"},"border":"#5d8ac2","syntax":{"field":"#8fc6e3","preproc":"#d94848","comment":"#699856","function":"#5d8ac2","operator":"#5d8ac2","constructor":"#84D9AA","property":"#d4d198","punctuation":"#5d8ac2","parameter":"#8fc6e3","variable":"#d94848","include":"#d94848","string":"#A3BE8C","type":"#d94848","number":"#B4CDA8","todo":{"bg":"#d4d198","fg":"#2e3440"},"struct":"#d94848","constant":"#5d8ac2","keyword":"#5d8ac2"},"built_in":{"function":"#d4d198","constant":"#5d8ac2","variable":"#8fc6e3","keyword":"#5d8ac2","type":"#d4d198"},"accent":"#5d8ac2"}