{"diagnostic":{"hint":"#5d8ac2","error":"#d94848","warn":"#d4d198","info":"#d94848"},"dimmed":{"subtle":"#4c566a","inactive":"#4C566A"},"red":"#d94848","pum":{"bg":"#2e3440","sel":{"bg":"#3E4452"},"fg":"#3B4252","sbar":"#3E4452","thumb":"#E5E9F0"},"green":"#98C379","uri":"#d94848","diff":{"text":"#5d8ac2","remove":"#d94848","add":"#98C379","change":"#d4d198"},"magenta":"#c487b9","blue":"#5d8ac2","remaps":{"langs":{"md":{"markdownCode":{"fg":"#A3BE8C"}}},"plugins":{"cmp":{"CmpItemAbbr":{"fg":"#E5E9F0"},"CmpItemMenu":{"fg":"#5d8ac2"},"CmpItemKind":{"fg":"#5d8ac2"},"CmpItemAbbrMatch":{"fg":"#8fc6e3"},"CmpItemKindVariable":{"fg":"#8fc6e3"}},"trouble":{"TroubleSignError":{"fg":"#d94848"},"TroubleSignWarning":{"fg":"#d4d198"}},"gitsigns":{"GitSignsChange":{"bg":"#2e3440","fg":"#d4d198"},"GitSignsDelete":{"fg":"#d94848"}},"lsp":{"DiagnosticUnderlineHint":{"fg":"NONE","style":"underline","sp":"#8fc6e3"},"DiagnosticUnderlineWarn":{"fg":"NONE","style":"underline","sp":"#d4d198"}},"telescope":{"TelescopePromptBorder":{"bg":"#2b2e36","fg":"#2e3440"},"TelescopeResultsNormal":{"bg":"#2b2e36"},"TelescopePromptNormal":{"bg":"#2b2e36","fg":"#E5E9F0"},"TelescopeBorder":{"bg":"#2b2e36","fg":"#2b2e36"},"TelescopeMatching":{"fg":"#5d8ac2"},"TelescopeSelectionCaret":{"bg":"#2b2e36","fg":"#2b2e36"},"TelescopePromptPrefix":{"bg":"#2b2e36","fg":"#5d8ac2"},"TelescopePreviewTitle":{"bg":"#98C379","fg":"#2b2e36"},"TelescopeSelection":{"bg":"#434c5e"},"TelescopePromptTitle":{"bg":"#d4d198","fg":"#2b2e36"},"TelescopePreviewNormal":{"bg":"#2b2e36"},"TelescopeResultsTitle":{"bg":"#5d8ac2","fg":"#2b2e36"}},"nvim_tree":{"NvimTreeRootFolder":{"fg":"#8fc6e3"},"NvimTreeGitDirty":{"fg":"#d4d198"},"NvimTreeFileDeleted":{"fg":"#d94848"},"NvimTreeGitDeleted":{"fg":"#d94848"}},"treesitter":{"@boolean":{"link":"Boolean"},"TSLabel":{"link":"String"},"@conditional":{"link":"Keyword"},"@keyword":{"fg":"#5d8ac2"},"TSNamespace":{"fg":"#4EC9B0"},"@function":{"link":"Function"},"@constant.builtin":{"link":"Keyword"},"TSKeywordFunction":{"link":"Keyword"},"TSType":{"fg":"#4EC9B0"},"TSConstructor":{"fg":"#5d8ac2"},"TSPunctBracket":{"fg":"#5d8ac2"},"@function.macro":{"link":"Function"},"TSConstant":{"link":"Constant"},"TSTitle":{"link":"String"},"TSKeyword":{"fg":"#5d8ac2"},"@property":{"link":"TSField"},"TSField":{"fg":"#8fc6e3"},"@function.builtin":{"link":"Function"},"TSVariable":{"link":"TSField"},"@text.title":{"link":"String"},"@constant":{"link":"Constant"},"TSTag":{"link":"Keyword"},"@tag":{"link":"Keyword"},"TSVariableBuiltin":{"link":"Keyword"},"@field":{"fg":"#8fc6e3"},"@variable.builtin":{"link":"Keyword"},"TSInclude":{"link":"Keyword"},"@include":{"link":"Keyword"},"TSConstBuiltin":{"link":"Keyword"},"TSConditional":{"link":"Keyword"},"@character":{"link":"Character"},"@keyword.function":{"link":"Keyword"},"TSMethod":{"link":"Function"},"@method":{"link":"Function"},"TSTypeBuiltin":{"fg":"#5d8ac2"},"@constructor":{"fg":"#5d8ac2"},"@punctuation.bracket":{"fg":"#5d8ac2"},"TSBoolean":{"link":"Boolean"},"@variable":{"link":"TSField"},"@label":{"link":"String"},"TSProperty":{"link":"TSField"},"@type.builtin":{"fg":"#5d8ac2"},"@namespace":{"fg":"#4EC9B0"},"@type":{"fg":"#4EC9B0"},"TSFuncMacro":{"link":"Function"},"TSFuncBuiltin":{"link":"Function"},"@error":{"link":"Error"},"TSError":{"link":"Error"},"TSFunction":{"link":"Function"},"TSCharacter":{"link":"Character"}}},"base":{"IncSearch":{"bg":"#699856","fg":"#d4d198"},"Special":{"fg":"#5d8ac2"},"Function":{"fg":"#d4d198"},"Type":{"fg":"#5d8ac2"},"EndOfBuffer":{"fg":"#2e3440"},"NonText":{"fg":"#5d8ac2"},"FloatBorder":{"fg":"#E5E9F0"},"PreProc":{"link":"Statement"},"Statement":{"fg":"#5d8ac2"},"TabLineSel":{"fg":"#E5E9F0"},"TabLine":{"fg":"#699856"},"ColorColumn":{"fg":"#d94848"},"Folded":{"fg":"#699856"},"Identifier":{"fg":"#8fc6e3"},"Normal":{"bg":"#2e3440","fg":"#E5E9F0"},"Float":{"link":"Number"},"TabLineFill":{"bg":"#2e3440"},"CursorLine":{"bg":"#3B4252"},"Boolean":{"link":"Constant"},"Whitespace":{"fg":"#E5E9F0"},"Number":{"fg":"#B4CDA8"},"Constant":{"fg":"#5d8ac2"},"Character":{"link":"String"},"Visual":{"bg":"#3E4452"},"Directory":{"fg":"#5d8ac2"},"WarningMsg":{"fg":"#d4d198"},"Search":{"bg":"#5d8ac2"},"VertSplit":{"bg":"#2e3440","fg":"#373e4a"},"MatchParen":{"bg":"#5d8ac2","fg":"#E5E9F0"},"ErrorMsg":{"bg":"#d94848","fg":"#E5E9F0"},"CursorLineNr":{"fg":"#E5E9F0"}}},"gitsigns":{"text":"#5d8ac2","remove":"#d94848","add":"#98C379","change":"#d4d198"},"scheme-name":"papa_dark","border":"#5d8ac2","heading":{"h2":"#d94848","h1":"#d94848"},"orange":"#d08770","syntax":{"function":"#5d8ac2","include":"#d94848","string":"#A3BE8C","struct":"#d94848","number":"#B4CDA8","type":"#d94848","todo":{"bg":"#d4d198","fg":"#2e3440"},"constant":"#5d8ac2","parameter":"#8fc6e3","preproc":"#d94848","keyword":"#5d8ac2","comment":"#699856","operator":"#5d8ac2","constructor":"#84D9AA","punctuation":"#5d8ac2","property":"#d4d198","variable":"#d94848","field":"#8fc6e3"},"accent":"#5d8ac2","yellow":"#d4d198","bg":{"alt":"#2b2e36","selected":"#3B4252","base":"#2e3440"},"match":"#E5E9F0","cyan":"#4EC9B0","search_result":{"fg":"#c487b9","telescope":"#5d8ac2","bg":"#2e3440"},"built_in":{"keyword":"#5d8ac2","type":"#d4d198","function":"#d4d198","variable":"#8fc6e3","constant":"#5d8ac2"}}