{"syntax":{"comment":"#6e6a86","property":"#907aa9","conditional":"#957fb8","operator":"#6e6a86","function":"#d7827e","include":"#907aa9","variable":"#575279","type":"#7aa89f","field":"#56949f","statement":"#286983","parameter":"#907aa9","constructor":"#56949f","string":"#ea9d34","number":"#ea9d34","struct":"#56949f","keyword":"#286983","tag":"#56949f","punctuation":"#6e6a86","todo":{"bg":"#0","fg":"#907aa9"},"preproc":"#907aa9","constant":"#56949f"},"diff":{"add":"#a8c4c6","remove":"#d7acb4","text":"#e9bbb6","change":"#f2e9de"},"pum":{"sbar":"#f2e9de","fg":"#6e6a86","thumb":"#9893a5","bg":"#fffaf3","sel":{"bg":"#f2e9de","fg":"#575279"}},"gitsigns":{"add":"#a8c4c6","remove":"#d7acb4","text":"#e9bbb6","change":"#f2e9de"},"diagnostic":{"hint":"#907aa9","info":"#56949f","error":"#b4637a","warn":"#ea9d34"},"border":"#6e6a86","built_in":{"function":"#b4637a","keyword":"#957fb8","constant":"#b4637a","variable":"#b4637a","type":"#7aa89f"},"orange":"#ea9d34","uri":"#ea9d34","blue":"#56949f","cursorlinenr":"#575279","dimmed":{"inactive":"#9893a5","subtle":"#6e6a86"},"fg":"#575279","search_result":{"bg":"#cecacd","fg":"#907aa9","telescope":"#dcd7ba"},"scheme-name":"rose_pine_dawn","accent":"#d7827e","match":"#575279","inc_search":{"bg":"#dfdad9","fg":"#0"},"magenta":"#907aa9","cyan":"#d7827e","green":"#286983","yellow":"#ea9d34","bg":{"base":"#faf4ed","selected":"#f4ede8","alt":"#fffaf3"},"heading":{"h1":"#907aa9","h2":"#0"}}