{"diagnostic":{"hint":"#907aa9","warn":"#ea9d34","info":"#56949f","error":"#b4637a"},"diff":{"change":"#f2e9de","add":"#a8c4c6","text":"#e9bbb6","remove":"#d7acb4"},"cursorlinenr":"#575279","search_result":{"fg":"#907aa9","telescope":"#dcd7ba","bg":"#cecacd"},"syntax":{"constant":"#56949f","tag":"#56949f","preproc":"#907aa9","function":"#d7827e","conditional":"#957fb8","constructor":"#56949f","todo":{"bg":"#0","fg":"#907aa9"},"struct":"#56949f","number":"#ea9d34","property":"#907aa9","statement":"#286983","punctuation":"#6e6a86","variable":"#575279","string":"#ea9d34","keyword":"#286983","parameter":"#907aa9","comment":"#6e6a86","type":"#7aa89f","operator":"#6e6a86","field":"#56949f","include":"#907aa9"},"bg":{"alt":"#fffaf3","base":"#faf4ed","selected":"#f4ede8"},"heading":{"h1":"#907aa9","h2":"#0"},"inc_search":{"bg":"#dfdad9","fg":"#0"},"fg":"#575279","blue":"#56949f","gitsigns":{"change":"#f2e9de","add":"#a8c4c6","text":"#e9bbb6","remove":"#d7acb4"},"scheme-name":"rose_pine_dawn","match":"#575279","accent":"#d7827e","border":"#6e6a86","magenta":"#907aa9","uri":"#ea9d34","yellow":"#ea9d34","pum":{"sbar":"#f2e9de","thumb":"#9893a5","bg":"#fffaf3","sel":{"bg":"#f2e9de","fg":"#575279"},"fg":"#6e6a86"},"orange":"#ea9d34","green":"#286983","built_in":{"function":"#b4637a","type":"#7aa89f","variable":"#b4637a","constant":"#b4637a","keyword":"#957fb8"},"dimmed":{"subtle":"#6e6a86","inactive":"#9893a5"},"cyan":"#d7827e"}