{"orange":"#f6c177","scheme-name":"rose_pine_moon","diagnostic":{"info":"#9ccfd8","hint":"#c4a7e7","warn":"#f6c177","error":"#eb6f92"},"dimmed":{"inactive":"#59546d","subtle":"#817c9c"},"bg":{"alt":"#2a273f","base":"#232136","selected":"#2a283e"},"accent":"#ea9a97","magenta":"#c4a7e7","diff":{"change":"#393552","add":"#607887","remove":"#874864","text":"#875e67"},"heading":{"h1":"#c4a7e7","h2":"#0"},"pum":{"sbar":"#393552","bg":"#2a273f","fg":"#817c9c","sel":{"fg":"#e0def4","bg":"#393552"},"thumb":"#59546d"},"gitsigns":{"change":"#393552","add":"#607887","remove":"#874864","text":"#875e67"},"match":"#e0def4","inc_search":{"fg":"#0","bg":"#44415a"},"search_result":{"fg":"#c4a7e7","bg":"#56526e","telescope":"#dcd7ba"},"cursorlinenr":"#e0def4","built_in":{"constant":"#eb6f92","type":"#7aa89f","keyword":"#957fb8","function":"#eb6f92","variable":"#eb6f92"},"fg":"#e0def4","green":"#3e8fb0","cyan":"#ea9a97","uri":"#f6c177","blue":"#9ccfd8","border":"#817c9c","yellow":"#f6c177","syntax":{"tag":"#9ccfd8","todo":{"fg":"#c4a7e7","bg":"#0"},"statement":"#3e8fb0","include":"#c4a7e7","comment":"#817c9c","preproc":"#c4a7e7","variable":"#e0def4","number":"#f6c177","parameter":"#c4a7e7","constructor":"#9ccfd8","function":"#ea9a97","keyword":"#3e8fb0","struct":"#9ccfd8","property":"#c4a7e7","field":"#9ccfd8","string":"#f6c177","constant":"#9ccfd8","punctuation":"#817c9c","type":"#7aa89f","conditional":"#957fb8","operator":"#817c9c"}}