{"bg":{"alt":"#303030","base":"#1c1b19","selected":"#303030"},"accent":"#ff5f00","fg":"#fce8c3","syntax":{"struct":"#aaeb3","punctuation":"#918175","preproc":"#aaeb3","type":"#baa67f","comment":"#918175","constant":"#ff5c8f","string":"#98bc37","keyword":"#ef2f27","include":"#aaeb3","function":"#fbb829","variable":"#fce8c3","tag":"#2c78bf","constructor":"#ff5f00","number":"#ff5c8f","statement":"#ef2f27","field":"#519f50","property":"#68a8e4","conditional":"#ef2f27","todo":{"fg":"#fce8c3","bg":"#1c1b19"},"operator":"#fce8c3","parameter":"#aaeb3"},"search_result":{"fg":"#0","telescope":"#e02c6d","bg":"#4e4e4e"},"built_in":{"keyword":"#ef2f27","function":"#fbb829","type":"#68a8e4","variable":"#aaeb3","constant":"#aaeb3"},"orange":"#FED06E","match":"#0","magenta":"#E02C6D","heading":{"h2":"#0","h1":"#0"},"blue":"#2C78BF","dimmed":{"subtle":"#918175","inactive":"#444444"},"scheme-name":"scery","cursorlinenr":"#fbb829","inc_search":{"bg":"#4e4e4e","fg":"#0"},"green":"#519F50","gitsigns":{"add":"#1c1b19","remove":"#1c1b19","change":"#1c1b19","text":"#1c1b19"},"border":"#fce8c3","uri":"#519f50","pum":{"bg":"#303030","sel":{"bg":"#2c78bf","fg":"#fce8c3"},"fg":"#fce8c3","thumb":"#1c1b19","sbar":"#1c1b19"},"cyan":"#0AAEB3","diff":{"add":"#1c1b19","remove":"#1c1b19","change":"#1c1b19","text":"#1c1b19"},"diagnostic":{"hint":"#d3d3d3","warn":"#ffa500","info":"#add8e6","error":"#ff0000"},"yellow":"#FBB829"}