{"magenta":"#bb9af7","fg":"#c0caf5","green":"#9ece6a","directory":"#7aa2f7","pum":{"bg":"#1f2335","fg":"#c0caf5","sbar":"#222229","sel":{"bg":"#343A55","fg":"#c0caf5"},"thumb":"#3b4261"},"orange":"#ff9e64","yellow":"#e0af68","red":"#f7768e","diagnostic":{"hint":"#1abc9c","warn":"#e0af68","info":"#0db9d7","error":"#db4b4b"},"accent":"#2ac3de","border":"#1D202F","uri":"#c0caf5","heading":{"h1":"#bb9af7","h2":"#7aa2f7"},"blue":"#7aa2f7","search_result":{"bg":"#3d59a1","telescope":"#c0caf5","fg":"#c0caf5"},"scheme-name":"tokyonight","inc_search":{"bg":"#ff9e64","fg":"#1D202F"},"bg":{"selected":"#292e42","alt":"#24283b","base":"#1a1b26"},"built_in":{"type":"#2ac3de","constant":"#2ac3de","variable":"#f7768e","function":"#2ac3de","keyword":"#bb9af7"},"diff":{"change":"#272D43","add":"#283B4D","remove":"#3F2D3D","text":"#394b70"},"cyan":"#7dcfff","dimmed":{"linenr":"#3b4261","inactive":"#545c7e","subtle":"#a9b1d6"},"syntax":{"struct":"#ff9e64","field":"#73daca","variable":"#c0caf5","punctuation":"#a9b1d6","keyword":"#bb9af7","property":"#73daca","constant":"#ff9e64","include":"#7dcfff","function":"#7aa2f7","statement":"#bb9af7","parameter":"#e0af68","operator":"#89ddff","constructor":"#bb9af7","todo":{"fg":"#1a1b26","bg":"#e0af68"},"conditional":"#bb9af7","type":"#2ac3de","preproc":"#7dcfff","comment":"#565f89","number":"#ff9e64","string":"#9ece6a"},"match":"#2ac3de","gitsigns":{"change":"#272D43","add":"#283B4D","remove":"#3F2D3D","text":"#394b70"}}